avahi_json/__init__.py
avahi_json/main.py
avahi_json-1.0.0.dist-info/METADATA
avahi_json-1.0.0.dist-info/WHEEL
avahi_json-1.0.0.dist-info/entry_points.txt
avahi_json-1.0.0.dist-info/top_level.txt
avahi_json-1.0.0.dist-info/RECORD
