Metadata-Version: 2.4
Name: avahi-json
Version: 1.0.0
Summary: Output details of hosts on the network found by Linux's avahi mdns server in JSON. 
Author-email: "@readwithai" <talwrii@github.com>
Project-URL: Homepage, https://github.com/talwrii/avahi-json
Requires-Dist: frozendict
